admetool/__init__.py
admetool/app.py
admetool/models.py
admetool-3.5.0.data/scripts/app.py
admetool-3.5.0.dist-info/LICENSE
admetool-3.5.0.dist-info/METADATA
admetool-3.5.0.dist-info/WHEEL
admetool-3.5.0.dist-info/entry_points.txt
admetool-3.5.0.dist-info/top_level.txt
admetool-3.5.0.dist-info/RECORD
