Metadata-Version: 2.1
Name: admetool
Version: 3.5.0
Summary: Tool that uses Pharmit data to perform an ADMET analysis
Author: Júlio César Xavier
Author-email: jcaxavier2@gmail.com
License: MIT License
Keywords: admetlab
License-File: LICENSE
Requires-Dist: pandas ==2.2.2
Requires-Dist: rdkit ==2023.9.6
Requires-Dist: numpy ==1.26.4
Requires-Dist: XlsxWriter ==3.2.0
Requires-Dist: openpyxl ==3.1.5
